odoo/addons/web_widget_one2many_product_picker_sale_stock_available_info_popup/README.rst
odoo/addons/web_widget_one2many_product_picker_sale_stock_available_info_popup/__init__.py
odoo/addons/web_widget_one2many_product_picker_sale_stock_available_info_popup/__manifest__.py
odoo/addons/web_widget_one2many_product_picker_sale_stock_available_info_popup/i18n/web_widget_one2many_product_picker_sale_stock_available_info_popup.pot
odoo/addons/web_widget_one2many_product_picker_sale_stock_available_info_popup/readme/CONTRIBUTORS.rst
odoo/addons/web_widget_one2many_product_picker_sale_stock_available_info_popup/readme/DESCRIPTION.rst
odoo/addons/web_widget_one2many_product_picker_sale_stock_available_info_popup/static/description/icon.png
odoo/addons/web_widget_one2many_product_picker_sale_stock_available_info_popup/static/description/index.html
odoo/addons/web_widget_one2many_product_picker_sale_stock_available_info_popup/static/src/js/views/abstract_view.js
odoo/addons/web_widget_one2many_product_picker_sale_stock_available_info_popup/templates/assets.xml
odoo12_addon_web_widget_one2many_product_picker_sale_stock_available_info_popup-12.0.1.0.1.dist-info/METADATA
odoo12_addon_web_widget_one2many_product_picker_sale_stock_available_info_popup-12.0.1.0.1.dist-info/WHEEL
odoo12_addon_web_widget_one2many_product_picker_sale_stock_available_info_popup-12.0.1.0.1.dist-info/top_level.txt
odoo12_addon_web_widget_one2many_product_picker_sale_stock_available_info_popup-12.0.1.0.1.dist-info/RECORD
