Metadata-Version: 2.1
Name: odoo12-addon-web-widget-one2many-product-picker-sale-stock-available-info-popup
Version: 12.0.1.0.1
Summary: Adds support for stock in the one2many product picker widget
Home-page: https://github.com/OCA/web
Author: Tecnativa, Odoo Community Association (OCA)
Author-email: support@odoo-community.org
License: AGPL-3
Platform: UNKNOWN
Classifier: Programming Language :: Python
Classifier: Framework :: Odoo
Classifier: Framework :: Odoo :: 12.0
Classifier: License :: OSI Approved :: GNU Affero General Public License v3
Requires-Python: >=3.5
Requires-Dist: odoo12-addon-sale-stock-available-info-popup
Requires-Dist: odoo12-addon-web-widget-one2many-product-picker-sale-stock
Requires-Dist: odoo (<12.1dev,>=12.0a)
